LICENSE
MANIFEST.in
README
setup.py
src/sleipnir/__init__.py
src/sleipnir.transport.egg-info/PKG-INFO
src/sleipnir.transport.egg-info/SOURCES.txt
src/sleipnir.transport.egg-info/dependency_links.txt
src/sleipnir.transport.egg-info/namespace_packages.txt
src/sleipnir.transport.egg-info/not-zip-safe
src/sleipnir.transport.egg-info/requires.txt
src/sleipnir.transport.egg-info/top_level.txt
src/sleipnir/transport/__init__.py
src/sleipnir/transport/compression.py
src/sleipnir/transport/connections.py
src/sleipnir/transport/constants.py
src/sleipnir/transport/enums.py
src/sleipnir/transport/errors.py
src/sleipnir/transport/parser.py
src/sleipnir/transport/serialization.py
src/sleipnir/transport/adapters/__init__.py
src/sleipnir/transport/adapters/pyside.py
src/sleipnir/transport/amqp/__init__.py
src/sleipnir/transport/amqp/builder.py
src/sleipnir/transport/amqp/channels.py
src/sleipnir/transport/amqp/connections.py
src/sleipnir/transport/amqp/messaging.py
src/sleipnir/transport/amqp/pools.py
src/sleipnir/transport/amqp/routes.py
src/sleipnir/transport/http/__init__.py
src/sleipnir/transport/http/connections.py
src/sleipnir/transport/patterns/__init__.py
src/sleipnir/transport/patterns/aggregators.py
src/sleipnir/transport/patterns/endpoints.py
src/sleipnir/transport/patterns/routers.py
src/sleipnir/transport/patterns/translators.py